src/data/__init__.py
src/data/master.py
src/data/personal_data/.gitkeep
src/main.py
src/menu/__init__.py
src/menu/index_menu.py
src/menu/new_password.py
src/utils/__init__.py
src/utils/crypto.py
src/utils/get_choice.py
src/utils/get_click_keyboard.py
password_manager_cli-0.1.6.dist-info/entry_points.txt
password_manager_cli-0.1.6.dist-info/WHEEL
password_manager_cli-0.1.6.dist-info/METADATA
password_manager_cli-0.1.6.dist-info/RECORD
