Metadata-Version: 2.1
Name: password-manager-cli
Version: 0.1.6
Summary: Password Manager CLI
Author: gbPagano
Author-email: guilhermebpagano@gmail.com
Requires-Python: >=3.10,<4.0
Classifier: Programming Language :: Python :: 3
Classifier: Programming Language :: Python :: 3.10
Requires-Dist: SQLAlchemy (>=1.4.39,<2.0.0)
Requires-Dist: argon2-cffi (>=21.3.0,<22.0.0)
Requires-Dist: click (>=8.1.3,<9.0.0)
Requires-Dist: cryptography (>=37.0.4,<38.0.0)
Requires-Dist: python-dotenv (>=0.20.0,<0.21.0)
Requires-Dist: rich (>=12.5.1,<13.0.0)
